Veripeditus-1.0.0a2-py3.5-nspkg.pth
Veripeditus-1.0.0a2.dist-info/DESCRIPTION.rst
Veripeditus-1.0.0a2.dist-info/METADATA
Veripeditus-1.0.0a2.dist-info/RECORD
Veripeditus-1.0.0a2.dist-info/WHEEL
Veripeditus-1.0.0a2.dist-info/entry_points.txt
Veripeditus-1.0.0a2.dist-info/metadata.json
Veripeditus-1.0.0a2.dist-info/namespace_packages.txt
Veripeditus-1.0.0a2.dist-info/top_level.txt
veripeditus/editor/__init__.py
veripeditus/editor/repo.py
veripeditus/editor/sdk.py
veripeditus/editor/util.py
veripeditus/editor/data/template_init.py
veripeditus/editor/data/template_setup.py
veripeditus/framework/__init__.py
veripeditus/framework/model.py
veripeditus/framework/util.py
veripeditus/framework/data/avatar_chess.svg
veripeditus/framework/data/avatar_default.svg
veripeditus/framework/data/avatar_dolphin.svg
veripeditus/framework/data/avatar_fox.svg
veripeditus/framework/data/avatar_ghost.svg
veripeditus/framework/data/avatar_kangaroo.svg
veripeditus/framework/data/avatar_pinkmonster.svg
veripeditus/framework/data/avatar_rappertux.svg
veripeditus/framework/data/avatar_rat.svg
veripeditus/framework/data/avatar_santa.svg
veripeditus/framework/data/avatar_schoolkid.svg
veripeditus/framework/data/avatar_squirrel.svg
veripeditus/framework/data/dummy.svg
veripeditus/game/test/__init__.py
veripeditus/game/test/data/apple.svg
veripeditus/game/test/data/beer.svg
veripeditus/server/__init__.py
veripeditus/server/app.py
veripeditus/server/auth.py
veripeditus/server/control.py
veripeditus/server/db.py
veripeditus/server/model.py
veripeditus/server/rest.py
veripeditus/server/sources.py
veripeditus/server/util.py
