Metadata-Version: 2.0
Name: Veripeditus
Version: 1.0.0a2
Summary: UNKNOWN
Home-page: http://www.veripeditus.org
Author: The Veripeditus Team and contributors
Author-email: team@veripeditus.org
License: UNKNOWN
Platform: UNKNOWN
Classifier: Development Status :: 3 - Alpha
Classifier: Environment :: Web Environment
Classifier: Intended Audience :: Developers
Classifier: Intended Audience :: Education
Classifier: License :: OSI Approved :: GNU Affero General Public License v3 or later (AGPLv3+)
Classifier: Programming Language :: Python :: 3.5
Classifier: Topic :: Education
Classifier: Topic :: Games/Entertainment
Classifier: Topic :: Internet :: WWW/HTTP :: WSGI :: Application
Classifier: Topic :: Software Development :: Libraries :: Application Frameworks
Requires-Dist: Flask (>=0.10)
Requires-Dist: Flask-Restless (>=1.0.0b2.dev0)
Requires-Dist: Flask-SQLAlchemy
Requires-Dist: GitPython
Requires-Dist: OSMAlchemy
Requires-Dist: SQLAlchemy (>=1.1.0)
Requires-Dist: SQLAlchemy-Utils
Requires-Dist: Shapely
Requires-Dist: gpxpy
Requires-Dist: passlib
Requires-Dist: setuptools
